LICENSE
MANIFEST.in
README.md
setup.py
wikipedia2vec_SM002583/__init__.py
wikipedia2vec_SM002583/cli.py
wikipedia2vec_SM002583/dictionary.cpp
wikipedia2vec_SM002583/dump_db.cpp
wikipedia2vec_SM002583/link_graph.cpp
wikipedia2vec_SM002583/mention_db.cpp
wikipedia2vec_SM002583/wikipedia2vec.cpp
wikipedia2vec_SM002583.egg-info/PKG-INFO
wikipedia2vec_SM002583.egg-info/SOURCES.txt
wikipedia2vec_SM002583.egg-info/dependency_links.txt
wikipedia2vec_SM002583.egg-info/entry_points.txt
wikipedia2vec_SM002583.egg-info/requires.txt
wikipedia2vec_SM002583.egg-info/top_level.txt
wikipedia2vec_SM002583/utils/__init__.py
wikipedia2vec_SM002583/utils/random.cpp
wikipedia2vec_SM002583/utils/wiki_dump_reader.cpp
wikipedia2vec_SM002583/utils/wiki_page.cpp
wikipedia2vec_SM002583/utils/sentence_detector/__init__.py
wikipedia2vec_SM002583/utils/sentence_detector/icu_sentence_detector.cpp
wikipedia2vec_SM002583/utils/sentence_detector/sentence.cpp
wikipedia2vec_SM002583/utils/tokenizer/__init__.py
wikipedia2vec_SM002583/utils/tokenizer/base_tokenizer.cpp
wikipedia2vec_SM002583/utils/tokenizer/icu_tokenizer.cpp
wikipedia2vec_SM002583/utils/tokenizer/jieba_tokenizer.cpp
wikipedia2vec_SM002583/utils/tokenizer/mecab_tokenizer.cpp
wikipedia2vec_SM002583/utils/tokenizer/regexp_tokenizer.cpp
wikipedia2vec_SM002583/utils/tokenizer/token.cpp