Metadata-Version: 2.1
Name: wikipedia2vec-SM002583
Version: 0.1
Summary: A tool for learning vector representations of words and entities from Wikipedia
Home-page: https://github.com/samikshm/wikipedia2vec_SM002583
Author: Samiksha Manjunath 
Author-email: samiksha.manjunath@gmail.com
License: UNKNOWN
Download-URL: https://github.com/samikshm/wikipedia2vec_SM002583/archive/0.1.tar.gz
Keywords: wikipedia,embedding,wikipedia2vec
Platform: UNKNOWN
Classifier: Development Status :: 5 - Production/Stable
Classifier: Intended Audience :: Developers
Classifier: Natural Language :: English
Classifier: License :: OSI Approved :: Apache Software License
Classifier: Programming Language :: Python
Classifier: Programming Language :: Python :: 2.7
Classifier: Programming Language :: Python :: 3.3
Classifier: Programming Language :: Python :: 3.4
Classifier: Programming Language :: Python :: 3.5
Classifier: Programming Language :: Python :: 3.6
